cline/VERSION
cline/__init__.py
cline/cli_args.py
cline/cli_protocol.py
cline/exceptions.py
cline/py.typed
cline/cli/__init__.py
cline/cli/argument_parser_cli.py
cline/cli/cli.py
cline/cli/py.typed
cline/tasks/__init__.py
cline/tasks/help.py
cline/tasks/py.typed
cline/tasks/task.py
cline/tasks/version.py
cline-1.2.2.dist-info/LICENSE
cline-1.2.2.dist-info/METADATA
cline-1.2.2.dist-info/WHEEL
cline-1.2.2.dist-info/top_level.txt
cline-1.2.2.dist-info/RECORD
